makerlabs/__init__.py
makerlabs/classes.py
makerlabs/diybio_org.py
makerlabs/fablabs_io.py
makerlabs/hackaday_io.py
makerlabs/hackerspaces_org.py
makerlabs/makerfaire_com.py
makerlabs/makerspaces_make_co.py
makerlabs/makery_info.py
makerlabs/repaircafe_org.py
makerlabs/timeline.py
makerlabs/utils.py
makerlabs-0.32.dist-info/LICENSE.md
makerlabs-0.32.dist-info/METADATA
makerlabs-0.32.dist-info/WHEEL
makerlabs-0.32.dist-info/top_level.txt
makerlabs-0.32.dist-info/RECORD
