Metadata-Version: 2.1
Name: makerlabs
Version: 0.32
Home-page: https://github.com/openp2pdesign/makerlabs
Download-URL: https://github.com/openp2pdesign/makerlabs/releases/tag/v0.32
Author: Massimo Menichinelli
Author-email: info@openp2pdesign.org
Keywords: Fab Lab,Fab Lab,Makerspace,Hackerspace,Repair Cafes,Makers,DIYbio
Classifier: Development Status :: 3 - Alpha
Classifier: Topic :: Utilities
Classifier: Environment :: Web Environment
Classifier: Operating System :: OS Independent
Classifier: Intended Audience :: Science/Research
Classifier: Programming Language :: Python
Classifier: Programming Language :: Python :: 3
Classifier: License :: OSI Approved :: GNU Lesser General Public License v3 (LGPLv3)
License-File: LICENSE.md
Requires-Dist: bs4
Requires-Dist: certifi
Requires-Dist: charset-normalizer
Requires-Dist: geographiclib
Requires-Dist: geojson
Requires-Dist: geopy
Requires-Dist: idna
Requires-Dist: jellyfish
Requires-Dist: lxml
Requires-Dist: numpy
Requires-Dist: pandas
Requires-Dist: pathlib
Requires-Dist: pycountry
Requires-Dist: python-dateutil
Requires-Dist: pytz
Requires-Dist: requests
Requires-Dist: six
Requires-Dist: soupsieve
Requires-Dist: urllib3
Requires-Dist: us
